<slide title="Sites">
<link align="center" href="http://php.net/links">http://php.net/links</link>
<blurb>
 The focus of the PHP.net sites has been kept relatively focused on providing
 services vital to the development of the project -- we've especially stayed
 clear of an article-driven site, a jobs listing site, and trying to index all
 of the various PHP-based projects.
</blurb>
<list title="News and Tutorials">
 <bullet>http://phpbuilder.com/</bullet>
 <bullet>http://weberdev.com/</bullet>
 <bullet>http://devnetwork.net/</bullet>
 <bullet>http://zend.com/</bullet>
</list>
<list title="Code and Projects">
 <bullet>http://px.sklar.com/</bullet>
 <bullet>http://phpclasses.org/</bullet>
 <bullet>http://php.foundries.sf.net/</bullet>
 <bullet>http://freshmeat.net/browse/183/</bullet>
</list>
<list title="Magazines">
 <bullet>http://phpmag.de/ (German)</bullet>
 <bullet>http://zephpmag.com/ (French)</bullet>
 <bullet>http://www.php-mag.net/ (English)</bullet>
 <bullet>http://www.phparch.com/ (English)</bullet>
</list>
</slide>
