<?xml version="1.0" encoding="ISO-8859-1"?>
<slide>
<title>Introduction</title>
<list effect="slide" fontsize="3em">
<bullet>Who has Programmed in PHP?</bullet>
<bullet>Who has tried the demos for PHP-GTK?</bullet>
<bullet>Who has Programmed in PHP-GTK?</bullet>
</list>
<blurb effect="slide" fontsize="5em">Aims for today</blurb>

<list  effect="slide" fontsize="3em">
<bullet>Get to see what PHP-GTK can deliver</bullet>
<bullet>Learn some of the tricks</bullet>
<bullet>See some of the Mistakes..</bullet>
<bullet>Keep you awake!</bullet>
</list>
</slide>
