<slide title="PHProjekt">
<link href="http://www.phprojekt.com/" align="center">http://www.phprojekt.com/</link>
<list>
 <bullet>Includes calendar, contact manager, time card system, project manager, chat, forum, request tracker, webmail, file manager, notes, bookmarks, votingtodo list</bullet>
 <bullet>Supports MySQL, PotgreSQL, Oracle, Infromix, and Microsoft SQL Server</bullet>
 <bullet>Translated into 20 languages</bullet>
</list>

<image align="center" filename="slides/pragmatic/phprojekt.png" />
</slide>
