<slide title="Resources">
<break lines="1" />
<link fontsize="2em" marginleft="5em" leader="Slides: " href=":-:url:-:"/>
<link fontsize="2em" marginleft="5em" leader="__callStatic: " href="http://php.net/__callStatic"/>
<link fontsize="2em" marginleft="5em" leader="Closures: " href="http://php.net/closures"/>
<link fontsize="2em" marginleft="5em" leader="PHP-FPM: " href="http://php-fpm.org/"/>
<link fontsize="2em" marginleft="5em" leader="Garbage Collection: " href="http://php.net/gc"/>
<link fontsize="2em" marginleft="5em" leader="Goto: " href="http://php.net/goto"/>
<link fontsize="2em" marginleft="5em" leader="LSB: " href="http://php.net/lsb"/>
<link fontsize="2em" marginleft="5em" leader="Namespaces: " href="http://php.net/namespaces"/>
<link fontsize="2em" marginleft="5em" leader="NowDoc: " href="http://php.net/nowdoc"/>
<link fontsize="2em" marginleft="5em" leader="OpenSSL: " href="http://php.net/openssl"/>
</slide>

